{"version":1,"resource":"file:///home/arshan/.hidden/VSnotes/Arg%20Parsing.md","entries":[{"id":"AN2b.md","timestamp":1760578895402},{"id":"B8gz.md","timestamp":1760579698364},{"id":"qBvd.md","timestamp":1760579708755},{"id":"t7XB.md","timestamp":1760748541558},{"id":"5cb6.md","timestamp":1760840173314},{"id":"5MRe.md","timestamp":1760896886186},{"id":"hnkx.md","timestamp":1760896899566},{"id":"niEp.md","timestamp":1760897241980},{"id":"LTME.md","timestamp":1760899773686},{"id":"3gDu.md","timestamp":1760899884366}]}